hemlock_ax/__init__.py
hemlock_ax/_admin_route.py
hemlock_ax/acquisition.py
hemlock_ax/app.py
hemlock_ax/assign.py
hemlock_ax/models.py
hemlock_ax/testing.py
hemlock_ax-0.0.1.dist-info/LICENSE
hemlock_ax-0.0.1.dist-info/METADATA
hemlock_ax-0.0.1.dist-info/WHEEL
hemlock_ax-0.0.1.dist-info/top_level.txt
hemlock_ax-0.0.1.dist-info/RECORD
