Metadata-Version: 2.1
Name: hemlock-ax
Version: 0.0.1
Summary: A hemock extension for adaptive experimentation.
Home-page: https://dsbowen.gitlab.io/hemlock-ax
Author: Dillon Bowen
Author-email: dsbowen@wharton.upenn.edu
License: UNKNOWN
Platform: UNKNOWN
Classifier: Programming Language :: Python :: 3
Classifier: License :: OSI Approved :: MIT License
Classifier: Operating System :: OS Independent
Requires-Python: >=3.8
License-File: LICENSE
Requires-Dist: hemlock-survey (>=1.0.0)
Requires-Dist: numpy
Requires-Dist: redis
Requires-Dist: rq
Requires-Dist: statsmodels
